{
  "data": {
    "article": {},
    "attachments": {},
    "author_id": "1672761170040692739",
    "conversation_id": "2004906254741962768",
    "created_at": "2025-12-30T12:46:15.000Z",
    "edit_controls": {
      "editable_until": "2025-12-30T13:46:15.000Z",
      "edits_remaining": 5,
      "is_edit_eligible": false
    },
    "edit_history_tweet_ids": [
      "2005983772077088954"
    ],
    "entities": {
      "mentions": [
        {
          "end": 13,
          "id": "1678171777409875968",
          "start": 0,
          "username": "420420420CTL"
        }
      ]
    },
    "geo": {},
    "id": "2005983772077088954",
    "in_reply_to_user_id": "1678171777409875968",
    "lang": "zh",
    "note_tweet": {
      "entities": {}
    },
    "possibly_sensitive": false,
    "public_metrics": {
      "bookmark_count": 0,
      "impression_count": 0,
      "like_count": 0,
      "quote_count": 0,
      "reply_count": 0,
      "retweet_count": 0
    },
    "referenced_tweets": [
      {
        "id": "2004906254741962768",
        "type": "replied_to"
      }
    ],
    "reply_settings": "everyone",
    "text": "@420420420CTL дәІжҲҡ: йҳҝиҫҫиҘҝжҠҠдҪ йӮЈдёӘзҲҪзҲҪзҡ„дәәи–„иҚ·еҶҚз»ҷжҲ‘жқҘдёҖеҸЈе‘ў"
  },
  "includes": {
    "media": [
      {
        "height": 2048,
        "media_key": "3_2004906221896404993",
        "public_metrics": {},
        "type": "photo",
        "url": "https://pbs.twimg.com/media/G9LblhwbEAEc2iL.jpg",
        "width": 1536
      }
    ],
    "tweets": [
      {
        "article": {},
        "attachments": {},
        "author_id": "1672761170040692739",
        "conversation_id": "2004906254741962768",
        "created_at": "2025-12-30T12:46:15.000Z",
        "edit_controls": {
          "editable_until": "2025-12-30T13:46:15.000Z",
          "edits_remaining": 5,
          "is_edit_eligible": false
        },
        "edit_history_tweet_ids": [
          "2005983772077088954"
        ],
        "entities": {
          "mentions": [
            {
              "end": 13,
              "id": "1678171777409875968",
              "start": 0,
              "username": "420420420CTL"
            }
          ]
        },
        "geo": {},
        "id": "2005983772077088954",
        "in_reply_to_user_id": "1678171777409875968",
        "lang": "zh",
        "note_tweet": {
          "entities": {}
        },
        "possibly_sensitive": false,
        "public_metrics": {
          "bookmark_count": 0,
          "impression_count": 0,
          "like_count": 0,
          "quote_count": 0,
          "reply_count": 0,
          "retweet_count": 0
        },
        "referenced_tweets": [
          {
            "id": "2004906254741962768",
            "type": "replied_to"
          }
        ],
        "reply_settings": "everyone",
        "text": "@420420420CTL дәІжҲҡ: йҳҝиҫҫиҘҝжҠҠдҪ йӮЈдёӘзҲҪзҲҪзҡ„дәәи–„иҚ·еҶҚз»ҷжҲ‘жқҘдёҖеҸЈе‘ў"
      },
      {
        "article": {},
        "attachments": {
          "media_keys": [
            "3_2004906221896404993"
          ]
        },
        "author_id": "1678171777409875968",
        "conversation_id": "2004906254741962768",
        "created_at": "2025-12-27T13:24:35.000Z",
        "edit_controls": {
          "editable_until": "2025-12-27T14:24:35.000Z",
          "edits_remaining": 5,
          "is_edit_eligible": true
        },
        "edit_history_tweet_ids": [
          "2004906254741962768"
        ],
        "entities": {
          "urls": [
            {
              "display_url": "pic.x.com/Rj7by9l4Iv",
              "end": 41,
              "expanded_url": "https://x.com/420420420CTL/status/2004906254741962768/photo/1",
              "media_key": "3_2004906221896404993",
              "start": 18,
              "url": "https://t.co/Rj7by9l4Iv"
            }
          ]
        },
        "geo": {},
        "id": "2004906254741962768",
        "lang": "zh",
        "note_tweet": {
          "entities": {}
        },
        "possibly_sensitive": false,
        "public_metrics": {
          "bookmark_count": 1,
          "impression_count": 6781,
          "like_count": 71,
          "quote_count": 0,
          "reply_count": 9,
          "retweet_count": 1
        },
        "reply_settings": "everyone",
        "text": "е®¶йҮҢжқҘдәІжҲҡй—®жҲ‘иҝҷжҳҜд»Җд№ҲпјҢжҲ‘иҜҙжҳҜи–„иҚ· https://t.co/Rj7by9l4Iv"
      }
    ],
    "users": [
      {
        "created_at": "2023-06-25T00:18:56.000Z",
        "description": "еҫҲжІЎиҖҗеҝғ, и®ЁеҺҢдёҚи®ІдҝЎз”Ёзҡ„дәә",
        "id": "1672761170040692739",
        "name": "вҸҡFrankLauвҸҡ",
        "pinned_tweet_id": "1947313906676007224",
        "profile_image_url": "https://pbs.twimg.com/profile_images/1836611539790651392/AXAKc9L__normal.jpg",
        "protected": false,
        "public_metrics": {
          "followers_count": 40,
          "following_count": 58,
          "like_count": 821,
          "listed_count": 0,
          "media_count": 39,
          "tweet_count": 308
        },
        "username": "FrankkkkkkLau",
        "verified": false
      },
      {
        "created_at": "2023-07-09T22:38:41.000Z",
        "description": "ж”ҜжҢҒдәһжҙІеӨ§йә»еҗҲжі•еҢ–пјҢеӨ§йә»йҷӨзҪӘпјҢжӯЈиҰ–йҶ«зҷӮеӨ§йә»з”ЁйҖ”пјҢMTFрҹҸіпёҸвҖҚвҡ§пёҸрҹҸіпёҸвҖҚрҹҢҲLGBTQеҸӢеҘҪрҹ§‘вҖҚрҹӨқвҖҚрҹ§‘рҹ‘ӯеҸӘжңүxе’Ңи°·жӯҢйӣ»йғөиҒҜз№«ж–№ејҸпјҢжңғеӣһз§ҒдҝЎпјҢзӨҫзҫӨпјҡhttps://t.co/YwMarw2XdU",
        "entities": {
          "description": {
            "urls": [
              {
                "display_url": "x.com/i/communities/вҖҰ",
                "end": 93,
                "expanded_url": "https://x.com/i/communities/2002034506979750304",
                "start": 70,
                "url": "https://t.co/YwMarw2XdU"
              }
            ]
          }
        },
        "id": "1678171777409875968",
        "location": "Los Angeles, CA",
        "name": "йӮҰе°је…”weed_420пјҲеӨ§йә»/йӣ»еӯҗз…ҷпјү",
        "pinned_tweet_id": "1994233157906788612",
        "profile_image_url": "https://pbs.twimg.com/profile_images/1997869953601712128/tL9oqeh2_normal.jpg",
        "protected": false,
        "public_metrics": {
          "followers_count": 993,
          "following_count": 584,
          "like_count": 338,
          "listed_count": 0,
          "media_count": 109,
          "tweet_count": 756
        },
        "username": "420420420CTL",
        "verified": true
      }
    ]
  }
}