{
  "data": {
    "article": {},
    "attachments": {},
    "author_id": "1672761170040692739",
    "conversation_id": "2043189116129644662",
    "created_at": "2026-04-12T04:47:00.000Z",
    "edit_controls": {
      "editable_until": "2026-04-12T05:47:00.000Z",
      "edits_remaining": 5,
      "is_edit_eligible": true
    },
    "edit_history_tweet_ids": [
      "2043189116129644662"
    ],
    "entities": {},
    "geo": {},
    "id": "2043189116129644662",
    "lang": "zh",
    "note_tweet": {
      "entities": {}
    },
    "possibly_sensitive": false,
    "public_metrics": {
      "bookmark_count": 0,
      "impression_count": 0,
      "like_count": 0,
      "quote_count": 0,
      "reply_count": 0,
      "retweet_count": 0
    },
    "reply_settings": "everyone",
    "text": "好奇新疆和西藏能用 ss aead 或者 ss2022 连接内地其他省的机器嘛, 之前听群友说会被阻断"
  },
  "includes": {
    "tweets": [
      {
        "article": {},
        "attachments": {},
        "author_id": "1672761170040692739",
        "conversation_id": "2043189116129644662",
        "created_at": "2026-04-12T04:47:00.000Z",
        "edit_controls": {
          "editable_until": "2026-04-12T05:47:00.000Z",
          "edits_remaining": 5,
          "is_edit_eligible": true
        },
        "edit_history_tweet_ids": [
          "2043189116129644662"
        ],
        "entities": {},
        "geo": {},
        "id": "2043189116129644662",
        "lang": "zh",
        "note_tweet": {
          "entities": {}
        },
        "possibly_sensitive": false,
        "public_metrics": {
          "bookmark_count": 0,
          "impression_count": 0,
          "like_count": 0,
          "quote_count": 0,
          "reply_count": 0,
          "retweet_count": 0
        },
        "reply_settings": "everyone",
        "text": "好奇新疆和西藏能用 ss aead 或者 ss2022 连接内地其他省的机器嘛, 之前听群友说会被阻断"
      }
    ],
    "users": [
      {
        "created_at": "2023-06-25T00:18:56.000Z",
        "description": "某只卷毛狗的温良形态 | CNIX听床师 | Mandarin/English/Cantonese🆗",
        "entities": {
          "url": {
            "urls": [
              {
                "display_url": "g.cn",
                "end": 23,
                "expanded_url": "https://g.cn/",
                "start": 0,
                "url": "https://t.co/I4STCmJ4Xt"
              }
            ]
          }
        },
        "id": "1672761170040692739",
        "location": "距离你0.5km",
        "name": "⏚FrankLau⏚",
        "pinned_tweet_id": "2034926426202546677",
        "profile_image_url": "https://pbs.twimg.com/profile_images/1836611539790651392/AXAKc9L__normal.jpg",
        "protected": false,
        "public_metrics": {
          "followers_count": 52,
          "following_count": 73,
          "like_count": 1377,
          "listed_count": 0,
          "media_count": 59,
          "tweet_count": 371
        },
        "url": "https://t.co/I4STCmJ4Xt",
        "username": "FrankkkkkkLau",
        "verified": false
      }
    ]
  }
}