{
  "data": {
    "article": {},
    "attachments": {
      "media_keys": [
        "3_2073271855772004352"
      ]
    },
    "author_id": "1672761170040692739",
    "conversation_id": "2073269748494987308",
    "created_at": "2026-07-04T05:05:06.000Z",
    "edit_controls": {
      "editable_until": "2026-07-04T06:05:06.000Z",
      "edits_remaining": 5,
      "is_edit_eligible": false
    },
    "edit_history_tweet_ids": [
      "2073271863971868762"
    ],
    "entities": {
      "urls": [
        {
          "display_url": "pic.x.com/IOFSb4oUIp",
          "end": 40,
          "expanded_url": "https://x.com/FrankkkkkkLau/status/2073271863971868762/photo/1",
          "media_key": "3_2073271855772004352",
          "start": 17,
          "url": "https://t.co/IOFSb4oUIp"
        }
      ]
    },
    "geo": {},
    "id": "2073271863971868762",
    "in_reply_to_user_id": "1672761170040692739",
    "lang": "zh",
    "note_tweet": {
      "entities": {}
    },
    "possibly_sensitive": false,
    "public_metrics": {
      "bookmark_count": 0,
      "impression_count": 0,
      "like_count": 0,
      "quote_count": 0,
      "reply_count": 0,
      "retweet_count": 0
    },
    "referenced_tweets": [
      {
        "id": "2073269748494987308",
        "type": "replied_to"
      }
    ],
    "reply_settings": "everyone",
    "text": "草怎么安卓端还看不见info符号 https://t.co/IOFSb4oUIp"
  },
  "includes": {
    "media": [
      {
        "height": 2454,
        "media_key": "3_2073271855772004352",
        "public_metrics": {},
        "type": "photo",
        "url": "https://pbs.twimg.com/media/HMW9xKYa8AAJDLM.jpg",
        "width": 1200
      },
      {
        "height": 2474,
        "media_key": "3_2073266447737122816",
        "public_metrics": {},
        "type": "photo",
        "url": "https://pbs.twimg.com/media/HMW42X4bcAAzqLj.jpg",
        "width": 1200
      },
      {
        "height": 747,
        "media_key": "3_2073266545770553344",
        "public_metrics": {},
        "type": "photo",
        "url": "https://pbs.twimg.com/media/HMW48FFa4AAUuTq.png",
        "width": 888
      }
    ],
    "tweets": [
      {
        "article": {},
        "attachments": {
          "media_keys": [
            "3_2073271855772004352"
          ]
        },
        "author_id": "1672761170040692739",
        "conversation_id": "2073269748494987308",
        "created_at": "2026-07-04T05:05:06.000Z",
        "edit_controls": {
          "editable_until": "2026-07-04T06:05:06.000Z",
          "edits_remaining": 5,
          "is_edit_eligible": false
        },
        "edit_history_tweet_ids": [
          "2073271863971868762"
        ],
        "entities": {
          "urls": [
            {
              "display_url": "pic.x.com/IOFSb4oUIp",
              "end": 40,
              "expanded_url": "https://x.com/FrankkkkkkLau/status/2073271863971868762/photo/1",
              "media_key": "3_2073271855772004352",
              "start": 17,
              "url": "https://t.co/IOFSb4oUIp"
            }
          ]
        },
        "geo": {},
        "id": "2073271863971868762",
        "in_reply_to_user_id": "1672761170040692739",
        "lang": "zh",
        "note_tweet": {
          "entities": {}
        },
        "possibly_sensitive": false,
        "public_metrics": {
          "bookmark_count": 0,
          "impression_count": 0,
          "like_count": 0,
          "quote_count": 0,
          "reply_count": 0,
          "retweet_count": 0
        },
        "referenced_tweets": [
          {
            "id": "2073269748494987308",
            "type": "replied_to"
          }
        ],
        "reply_settings": "everyone",
        "text": "草怎么安卓端还看不见info符号 https://t.co/IOFSb4oUIp"
      },
      {
        "article": {},
        "attachments": {
          "media_keys": [
            "3_2073266447737122816",
            "3_2073266545770553344"
          ]
        },
        "author_id": "1672761170040692739",
        "conversation_id": "2073269748494987308",
        "created_at": "2026-07-04T04:56:42.000Z",
        "edit_controls": {
          "editable_until": "2026-07-04T05:56:42.000Z",
          "edits_remaining": 5,
          "is_edit_eligible": false
        },
        "edit_history_tweet_ids": [
          "2073269748494987308"
        ],
        "entities": {
          "urls": [
            {
              "display_url": "pic.x.com/sC7nthIuSq",
              "end": 55,
              "expanded_url": "https://x.com/FrankkkkkkLau/status/2073269748494987308/photo/1",
              "media_key": "3_2073266447737122816",
              "start": 32,
              "url": "https://t.co/sC7nthIuSq"
            },
            {
              "display_url": "pic.x.com/sC7nthIuSq",
              "end": 55,
              "expanded_url": "https://x.com/FrankkkkkkLau/status/2073269748494987308/photo/1",
              "media_key": "3_2073266545770553344",
              "start": 32,
              "url": "https://t.co/sC7nthIuSq"
            }
          ]
        },
        "geo": {},
        "id": "2073269748494987308",
        "lang": "zh",
        "note_tweet": {
          "entities": {}
        },
        "possibly_sensitive": false,
        "public_metrics": {
          "bookmark_count": 0,
          "impression_count": 52,
          "like_count": 6,
          "quote_count": 0,
          "reply_count": 2,
          "retweet_count": 0
        },
        "reply_settings": "everyone",
        "text": "为什么新注册的账号从安卓端看会有vpn标, web端看就是🛈︎ https://t.co/sC7nthIuSq"
      }
    ],
    "users": [
      {
        "created_at": "2023-06-25T00:18:56.000Z",
        "description": "某只卷毛狗的温良形态 | Prefer Simplified Chinese | Mandarin/English/Cantonese🆗\nLikes/RTs≠endorsements",
        "id": "1672761170040692739",
        "location": "Chinese Mainland",
        "name": "⏚FrankLau⏚",
        "pinned_tweet_id": "2068244369963118854",
        "profile_image_url": "https://pbs.twimg.com/profile_images/2059904056915804160/UHsopShb_normal.png",
        "protected": false,
        "public_metrics": {
          "followers_count": 496,
          "following_count": 563,
          "like_count": 6087,
          "listed_count": 1,
          "media_count": 279,
          "tweet_count": 1253
        },
        "url": "",
        "username": "FrankkkkkkLau",
        "verified": true
      }
    ]
  }
}