{
  "data": {
    "article": {},
    "attachments": {},
    "author_id": "1672761170040692739",
    "conversation_id": "2067270987637514242",
    "created_at": "2026-06-17T17:10:16.000Z",
    "edit_controls": {
      "editable_until": "2026-06-17T18:10:16.000Z",
      "edits_remaining": 5,
      "is_edit_eligible": false
    },
    "edit_history_tweet_ids": [
      "2067293765161955509"
    ],
    "entities": {
      "mentions": [
        {
          "end": 16,
          "id": "1732763258325762048",
          "start": 0,
          "username": "AmeAsukaLangley"
        }
      ]
    },
    "geo": {},
    "id": "2067293765161955509",
    "in_reply_to_user_id": "1732763258325762048",
    "lang": "qme",
    "note_tweet": {
      "entities": {}
    },
    "possibly_sensitive": false,
    "public_metrics": {
      "bookmark_count": 0,
      "impression_count": 0,
      "like_count": 0,
      "quote_count": 0,
      "reply_count": 0,
      "retweet_count": 0
    },
    "referenced_tweets": [
      {
        "id": "2067292727004565950",
        "type": "replied_to"
      }
    ],
    "reply_settings": "everyone",
    "text": "@AmeAsukaLangley 😽"
  },
  "includes": {
    "tweets": [
      {
        "article": {},
        "attachments": {},
        "author_id": "1672761170040692739",
        "conversation_id": "2067270987637514242",
        "created_at": "2026-06-17T17:10:16.000Z",
        "edit_controls": {
          "editable_until": "2026-06-17T18:10:16.000Z",
          "edits_remaining": 5,
          "is_edit_eligible": false
        },
        "edit_history_tweet_ids": [
          "2067293765161955509"
        ],
        "entities": {
          "mentions": [
            {
              "end": 16,
              "id": "1732763258325762048",
              "start": 0,
              "username": "AmeAsukaLangley"
            }
          ]
        },
        "geo": {},
        "id": "2067293765161955509",
        "in_reply_to_user_id": "1732763258325762048",
        "lang": "qme",
        "note_tweet": {
          "entities": {}
        },
        "possibly_sensitive": false,
        "public_metrics": {
          "bookmark_count": 0,
          "impression_count": 0,
          "like_count": 0,
          "quote_count": 0,
          "reply_count": 0,
          "retweet_count": 0
        },
        "referenced_tweets": [
          {
            "id": "2067292727004565950",
            "type": "replied_to"
          }
        ],
        "reply_settings": "everyone",
        "text": "@AmeAsukaLangley 😽"
      },
      {
        "article": {},
        "attachments": {},
        "author_id": "1732763258325762048",
        "conversation_id": "2067270987637514242",
        "created_at": "2026-06-17T17:06:09.000Z",
        "edit_controls": {
          "editable_until": "2026-06-17T18:06:09.000Z",
          "edits_remaining": 5,
          "is_edit_eligible": false
        },
        "edit_history_tweet_ids": [
          "2067292727004565950"
        ],
        "entities": {
          "mentions": [
            {
              "end": 14,
              "id": "1672761170040692739",
              "start": 0,
              "username": "FrankkkkkkLau"
            }
          ]
        },
        "geo": {},
        "id": "2067292727004565950",
        "in_reply_to_user_id": "1672761170040692739",
        "lang": "ja",
        "note_tweet": {
          "entities": {}
        },
        "possibly_sensitive": false,
        "public_metrics": {
          "bookmark_count": 0,
          "impression_count": 3,
          "like_count": 1,
          "quote_count": 0,
          "reply_count": 1,
          "retweet_count": 0
        },
        "referenced_tweets": [
          {
            "id": "2067287546074399023",
            "type": "replied_to"
          }
        ],
        "reply_settings": "everyone",
        "text": "@FrankkkkkkLau 感谢呀"
      }
    ],
    "users": [
      {
        "created_at": "2023-06-25T00:18:56.000Z",
        "description": "某只卷毛狗的温良形态 | Prefer Simplified Chinese | Mandarin/English/Cantonese🆗\nLikes/RTs≠endorsements",
        "id": "1672761170040692739",
        "location": "Chinese Mainland",
        "name": "⏚FrankLau⏚",
        "pinned_tweet_id": "2056283985509323165",
        "profile_image_url": "https://pbs.twimg.com/profile_images/2059904056915804160/UHsopShb_normal.png",
        "protected": false,
        "public_metrics": {
          "followers_count": 319,
          "following_count": 350,
          "like_count": 4501,
          "listed_count": 1,
          "media_count": 190,
          "tweet_count": 944
        },
        "username": "FrankkkkkkLau",
        "verified": true
      },
      {
        "created_at": "2023-12-07T14:05:39.000Z",
        "description": "恋人@marisa114514191 \n应是那永恒的未许之地。\n不是所有同类都互fo看主页有没有喜欢的内容\n欢迎匿名提问↓↓↓",
        "entities": {
          "description": {
            "mentions": [
              {
                "end": 18,
                "start": 2,
                "username": "marisa114514191"
              }
            ]
          },
          "url": {
            "urls": [
              {
                "display_url": "ngl.link/raincandyu",
                "end": 23,
                "expanded_url": "https://ngl.link/raincandyu",
                "start": 0,
                "url": "https://t.co/tFlSitR0OB"
              }
            ]
          }
        },
        "id": "1732763258325762048",
        "location": "玉川上水",
        "name": "raincandy_U",
        "pinned_tweet_id": "2061022848504991748",
        "profile_image_url": "https://pbs.twimg.com/profile_images/2053853903444381696/z7Kqgead_normal.jpg",
        "protected": false,
        "public_metrics": {
          "followers_count": 415,
          "following_count": 328,
          "like_count": 23296,
          "listed_count": 0,
          "media_count": 56,
          "tweet_count": 1620
        },
        "url": "https://t.co/tFlSitR0OB",
        "username": "AmeAsukaLangley",
        "verified": false
      }
    ]
  }
}