{
  "data": {
    "article": {},
    "attachments": {
      "media_keys": [
        "3_2075862736307941376"
      ]
    },
    "author_id": "1672761170040692739",
    "conversation_id": "2075862741697364447",
    "created_at": "2026-07-11T08:40:19.000Z",
    "edit_controls": {
      "editable_until": "2026-07-11T09:40:19.000Z",
      "edits_remaining": 5,
      "is_edit_eligible": true
    },
    "edit_history_tweet_ids": [
      "2075862741697364447"
    ],
    "entities": {
      "urls": [
        {
          "display_url": "pic.x.com/qPBJNUhjNE",
          "end": 30,
          "expanded_url": "https://x.com/FrankkkkkkLau/status/2075862741697364447/photo/1",
          "media_key": "3_2075862736307941376",
          "start": 7,
          "url": "https://t.co/qPBJNUhjNE"
        }
      ]
    },
    "geo": {},
    "id": "2075862741697364447",
    "lang": "zh",
    "note_tweet": {
      "entities": {}
    },
    "possibly_sensitive": false,
    "public_metrics": {
      "bookmark_count": 0,
      "impression_count": 0,
      "like_count": 0,
      "quote_count": 0,
      "reply_count": 0,
      "retweet_count": 0
    },
    "reply_settings": "everyone",
    "text": "?异常你卤味 https://t.co/qPBJNUhjNE"
  },
  "includes": {
    "media": [
      {
        "height": 601,
        "media_key": "3_2075862736307941376",
        "public_metrics": {},
        "type": "photo",
        "url": "https://pbs.twimg.com/media/HM7yKQga8AAVKK8.jpg",
        "width": 1200
      }
    ],
    "tweets": [
      {
        "article": {},
        "attachments": {
          "media_keys": [
            "3_2075862736307941376"
          ]
        },
        "author_id": "1672761170040692739",
        "conversation_id": "2075862741697364447",
        "created_at": "2026-07-11T08:40:19.000Z",
        "edit_controls": {
          "editable_until": "2026-07-11T09:40:19.000Z",
          "edits_remaining": 5,
          "is_edit_eligible": true
        },
        "edit_history_tweet_ids": [
          "2075862741697364447"
        ],
        "entities": {
          "urls": [
            {
              "display_url": "pic.x.com/qPBJNUhjNE",
              "end": 30,
              "expanded_url": "https://x.com/FrankkkkkkLau/status/2075862741697364447/photo/1",
              "media_key": "3_2075862736307941376",
              "start": 7,
              "url": "https://t.co/qPBJNUhjNE"
            }
          ]
        },
        "geo": {},
        "id": "2075862741697364447",
        "lang": "zh",
        "note_tweet": {
          "entities": {}
        },
        "possibly_sensitive": false,
        "public_metrics": {
          "bookmark_count": 0,
          "impression_count": 0,
          "like_count": 0,
          "quote_count": 0,
          "reply_count": 0,
          "retweet_count": 0
        },
        "reply_settings": "everyone",
        "text": "?异常你卤味 https://t.co/qPBJNUhjNE"
      }
    ],
    "users": [
      {
        "created_at": "2023-06-25T00:18:56.000Z",
        "description": "某只卷毛狗的温良形态 | Prefer Simplified Chinese | Mandarin/English/Cantonese🆗\nLikes/RTs≠endorsements",
        "id": "1672761170040692739",
        "location": "Chinese Mainland",
        "name": "⏚FrankLau⏚",
        "pinned_tweet_id": "2068244369963118854",
        "profile_image_url": "https://pbs.twimg.com/profile_images/2059904056915804160/UHsopShb_normal.png",
        "protected": false,
        "public_metrics": {
          "followers_count": 595,
          "following_count": 663,
          "like_count": 7363,
          "listed_count": 1,
          "media_count": 326,
          "tweet_count": 1495
        },
        "url": "",
        "username": "FrankkkkkkLau",
        "verified": true
      }
    ]
  }
}